frida_start/__init__.py
frida_start/command.py
frida_start-3.0.1.dist-info/METADATA
frida_start-3.0.1.dist-info/WHEEL
frida_start-3.0.1.dist-info/entry_points.txt
frida_start-3.0.1.dist-info/licenses/LICENSE
frida_start-3.0.1.dist-info/RECORD
