Metadata-Version: 2.3
Name: frida-start
Version: 3.0.1
Summary: Wrapper tool to identify the remote device and push device specific frida-server binary.
Project-URL: Source, https://github.com/davidpatel0/frida-start
License-Expression: GPL-3.0-or-later
License-File: LICENSE
Requires-Python: >=3.8
Requires-Dist: frida
Requires-Dist: requests
